overcooked/__init__.py
overcooked/env.py
overcooked/static.py
overcooked/utils.py
overcooked/data/fonts/Roboto-Regular.ttf
overcooked/data/graphics/arrow.png
overcooked/data/graphics/chefs.json
overcooked/data/graphics/chefs.png
overcooked/data/graphics/interact.png
overcooked/data/graphics/objects.json
overcooked/data/graphics/objects.png
overcooked/data/graphics/soups.json
overcooked/data/graphics/soups.png
overcooked/data/graphics/stay.png
overcooked/data/graphics/terrain.json
overcooked/data/graphics/terrain.png
overcooked/data/layouts/asymmetric_advantages.layout
overcooked/data/layouts/asymmetric_advantages_tomato.layout
overcooked/data/layouts/bonus_order_test.layout
overcooked/data/layouts/bottleneck.layout
overcooked/data/layouts/centre_objects.layout
overcooked/data/layouts/centre_pots.layout
overcooked/data/layouts/coordination_ring.layout
overcooked/data/layouts/corridor.layout
overcooked/data/layouts/counter_circuit.layout
overcooked/data/layouts/counter_circuit_o_1order.layout
overcooked/data/layouts/cramped_corridor.layout
overcooked/data/layouts/cramped_room.layout
overcooked/data/layouts/cramped_room_o_3orders.layout
overcooked/data/layouts/cramped_room_single.layout
overcooked/data/layouts/cramped_room_tomato.layout
overcooked/data/layouts/five_by_five.layout
overcooked/data/layouts/forced_coordination.layout
overcooked/data/layouts/forced_coordination_tomato.layout
overcooked/data/layouts/inverse_marshmallow_experiment.layout
overcooked/data/layouts/large_room.layout
overcooked/data/layouts/long_cook_time.layout
overcooked/data/layouts/m_shaped_s.layout
overcooked/data/layouts/marshmallow_experiment.layout
overcooked/data/layouts/marshmallow_experiment_coordination.layout
overcooked/data/layouts/mdp_test.layout
overcooked/data/layouts/multiplayer_schelling.layout
overcooked/data/layouts/old_dynamics_cook_test.layout
overcooked/data/layouts/old_dynamics_put_test.layout
overcooked/data/layouts/pipeline.layout
overcooked/data/layouts/random0.layout
overcooked-0.1.0.dist-info/METADATA
overcooked-0.1.0.dist-info/WHEEL
overcooked-0.1.0.dist-info/licenses/LICENSE
overcooked-0.1.0.dist-info/RECORD
