Metadata-Version: 2.4
Name: overcooked
Version: 0.1.0
Summary: Cooperative multi-agent environment based on Overcooked
Project-URL: repo, https://github.com/yamoling/overcooked
Project-URL: original_homepage, https://github.com/HumanCompatibleAI/overcooked_ai
Author-email: Yannick Molinghen <yannick.molinghen@ulb.be>, Yannick Molinghen <yannick.molinghen@gmail.com>, Micah Carroll <mdc@berkeley.edu>
License: MIT License
License-File: LICENSE
Keywords: AI,Overcooked,Reinforcement Learning
Requires-Python: >=3.10
Requires-Dist: gymnasium>=1.0.0
Requires-Dist: multi-agent-rlenv>=3.5.5
Requires-Dist: numpy>=2.0.0
Requires-Dist: opencv-python>=4.11.0.86
Requires-Dist: pygame>=2.6.1
Requires-Dist: scipy>=1.10
